Metadata-Version: 2.1
Name: aiogram-dev2
Version: 2.18
Summary: Is a pretty simple and fully asynchronous framework for Telegram Bot API
Home-page: https://github.com/aiogram/aiogram
Author: Alex Root Junior
Author-email: jroot.junior@gmail.com
License: MIT
Platform: UNKNOWN
Classifier: Development Status :: 5 - Production/Stable
Classifier: Environment :: Console
Classifier: Framework :: AsyncIO
Classifier: Intended Audience :: Developers
Classifier: Intended Audience :: System Administrators
Classifier: License :: OSI Approved :: MIT License
Classifier: Programming Language :: Python :: 3.7
Classifier: Programming Language :: Python :: 3.8
Classifier: Programming Language :: Python :: 3.9
Classifier: Programming Language :: Python :: 3.10
Classifier: Topic :: Software Development :: Libraries :: Application Frameworks
License-File: LICENSE
Requires-Dist: aiohttp (<3.9.0,>=3.8.0)
Requires-Dist: Babel (<2.10.0,>=2.9.1)
Requires-Dist: certifi (>=2021.10.8)
Provides-Extra: fast
Requires-Dist: uvloop (<0.17.0,>=0.16.0) ; extra == 'fast'
Requires-Dist: ujson (>=1.35) ; extra == 'fast'
Provides-Extra: proxy
Requires-Dist: aiohttp-socks (<0.6.0,>=0.5.3) ; extra == 'proxy'
